package com.google.android.gms.iid;

import android.os.IBinder;

class g
  implements e
{
  private IBinder a;
  
  g(IBinder paramIBinder)
  {
    a = paramIBinder;
  }
  
  /* Error */
  public void a(android.os.Message paramMessage)
    throws android.os.RemoteException
  {
    // Byte code:
    //   0: invokestatic 25	android/os/Parcel:obtain	()Landroid/os/Parcel;
    //   3: astore_2
    //   4: aload_2
    //   5: ldc 27
    //   7: invokevirtual 31	android/os/Parcel:writeInterfaceToken	(Ljava/lang/String;)V
    //   10: aload_1
    //   11: ifnull +33 -> 44
    //   14: aload_2
    //   15: iconst_1
    //   16: invokevirtual 35	android/os/Parcel:writeInt	(I)V
    //   19: aload_1
    //   20: aload_2
    //   21: iconst_0
    //   22: invokevirtual 41	android/os/Message:writeToParcel	(Landroid/os/Parcel;I)V
    //   25: aload_0
    //   26: getfield 15	com/google/android/gms/iid/g:a	Landroid/os/IBinder;
    //   29: iconst_1
    //   30: aload_2
    //   31: aconst_null
    //   32: iconst_1
    //   33: invokeinterface 47 5 0
    //   38: pop
    //   39: aload_2
    //   40: invokevirtual 50	android/os/Parcel:recycle	()V
    //   43: return
    //   44: aload_2
    //   45: iconst_0
    //   46: invokevirtual 35	android/os/Parcel:writeInt	(I)V
    //   49: goto -24 -> 25
    //   52: astore_1
    //   53: aload_2
    //   54: invokevirtual 50	android/os/Parcel:recycle	()V
    //   57: aload_1
    //   58: athrow
    // Local variable table:
    //   start	length	slot	name	signature
    //   0	59	0	this	g
    //   0	59	1	paramMessage	android.os.Message
    //   3	51	2	localParcel	android.os.Parcel
    // Exception table:
    //   from	to	target	type
    //   4	10	52	finally
    //   14	25	52	finally
    //   25	39	52	finally
    //   44	49	52	finally
  }
  
  public IBinder asBinder()
  {
    return a;
  }
}

/* Location:
 * Qualified Name:     com.google.android.gms.iid.g
 * Java Class Version: 6 (50.0)
 * JD-Core Version:    0.7.1
 */