package com.taplytics;

import android.os.AsyncTask;

class dn
  extends AsyncTask<Void, Void, Void>
{
  private dn(dg paramdg) {}
  
  /* Error */
  protected final Void a(Void... paramVarArgs)
  {
    // Byte code:
    //   0: iconst_0
    //   1: istore_3
    //   2: aload_0
    //   3: getfield 11	com/taplytics/dn:a	Lcom/taplytics/dg;
    //   6: invokestatic 26	com/taplytics/dg:a	(Lcom/taplytics/dg;)Ljava/lang/reflect/Method;
    //   9: ifnull +43 -> 52
    //   12: aload_0
    //   13: getfield 11	com/taplytics/dn:a	Lcom/taplytics/dg;
    //   16: invokestatic 29	com/taplytics/dg:b	(Lcom/taplytics/dg;)Ljava/lang/reflect/Method;
    //   19: ifnull +33 -> 52
    //   22: aload_0
    //   23: getfield 11	com/taplytics/dn:a	Lcom/taplytics/dg;
    //   26: invokestatic 33	com/taplytics/dg:c	(Lcom/taplytics/dg;)Ljava/lang/Class;
    //   29: ifnull +23 -> 52
    //   32: aload_0
    //   33: getfield 11	com/taplytics/dn:a	Lcom/taplytics/dg;
    //   36: invokestatic 36	com/taplytics/dg:d	(Lcom/taplytics/dg;)Ljava/lang/Class;
    //   39: ifnull +13 -> 52
    //   42: aload_0
    //   43: getfield 11	com/taplytics/dn:a	Lcom/taplytics/dg;
    //   46: getfield 40	com/taplytics/dg:g	[Ljava/lang/reflect/Field;
    //   49: ifnonnull +348 -> 397
    //   52: new 42	dalvik/system/DexFile
    //   55: dup
    //   56: invokestatic 48	com/taplytics/fy:e	()Lcom/taplytics/fy;
    //   59: invokevirtual 52	com/taplytics/fy:p	()Landroid/content/Context;
    //   62: invokevirtual 58	android/content/Context:getPackageCodePath	()Ljava/lang/String;
    //   65: invokespecial 61	dalvik/system/DexFile:<init>	(Ljava/lang/String;)V
    //   68: astore 6
    //   70: aload 6
    //   72: invokevirtual 65	dalvik/system/DexFile:entries	()Ljava/util/Enumeration;
    //   75: astore 7
    //   77: aload 7
    //   79: invokeinterface 71 1 0
    //   84: istore 5
    //   86: iload 5
    //   88: ifeq +98 -> 186
    //   91: aload 7
    //   93: invokeinterface 75 1 0
    //   98: checkcast 77	java/lang/String
    //   101: invokestatic 83	java/lang/Class:forName	(Ljava/lang/String;)Ljava/lang/Class;
    //   104: astore 8
    //   106: aload 8
    //   108: invokevirtual 87	java/lang/Class:getDeclaredFields	()[Ljava/lang/reflect/Field;
    //   111: astore_1
    //   112: aload_1
    //   113: ifnull -36 -> 77
    //   116: aload 8
    //   118: invokevirtual 90	java/lang/Class:getCanonicalName	()Ljava/lang/String;
    //   121: ldc 92
    //   123: invokevirtual 96	java/lang/String:contains	(Ljava/lang/CharSequence;)Z
    //   126: ifeq -49 -> 77
    //   129: aload_1
    //   130: arraylength
    //   131: bipush 30
    //   133: if_icmple -56 -> 77
    //   136: invokestatic 100	com/taplytics/ck:c	()Z
    //   139: ifeq +29 -> 168
    //   142: new 102	java/lang/StringBuilder
    //   145: dup
    //   146: invokespecial 103	java/lang/StringBuilder:<init>	()V
    //   149: ldc 105
    //   151: invokevirtual 109	java/lang/StringBuilder:append	(Ljava/lang/String;)Ljava/lang/StringBuilder;
    //   154: aload 8
    //   156: invokevirtual 90	java/lang/Class:getCanonicalName	()Ljava/lang/String;
    //   159: invokevirtual 109	java/lang/StringBuilder:append	(Ljava/lang/String;)Ljava/lang/StringBuilder;
    //   162: invokevirtual 112	java/lang/StringBuilder:toString	()Ljava/lang/String;
    //   165: invokestatic 114	com/taplytics/ck:a	(Ljava/lang/String;)V
    //   168: aload_0
    //   169: getfield 11	com/taplytics/dn:a	Lcom/taplytics/dg;
    //   172: aload 8
    //   174: invokestatic 117	com/taplytics/dg:a	(Lcom/taplytics/dg;Ljava/lang/Class;)Ljava/lang/Class;
    //   177: pop
    //   178: aload_0
    //   179: getfield 11	com/taplytics/dn:a	Lcom/taplytics/dg;
    //   182: aload_1
    //   183: putfield 40	com/taplytics/dg:g	[Ljava/lang/reflect/Field;
    //   186: aload 6
    //   188: invokevirtual 65	dalvik/system/DexFile:entries	()Ljava/util/Enumeration;
    //   191: astore 6
    //   193: aload 6
    //   195: invokeinterface 71 1 0
    //   200: istore 5
    //   202: iload 5
    //   204: ifeq +110 -> 314
    //   207: aload 6
    //   209: invokeinterface 75 1 0
    //   214: checkcast 77	java/lang/String
    //   217: invokestatic 83	java/lang/Class:forName	(Ljava/lang/String;)Ljava/lang/Class;
    //   220: astore 7
    //   222: aload 7
    //   224: invokevirtual 121	java/lang/Class:getDeclaredMethods	()[Ljava/lang/reflect/Method;
    //   227: astore_1
    //   228: aload_1
    //   229: ifnull +73 -> 302
    //   232: aload_1
    //   233: arraylength
    //   234: istore 4
    //   236: iconst_0
    //   237: istore_2
    //   238: iload_2
    //   239: iload 4
    //   241: if_icmpge +61 -> 302
    //   244: aload_1
    //   245: iload_2
    //   246: aaload
    //   247: invokevirtual 127	java/lang/reflect/Method:getReturnType	()Ljava/lang/Class;
    //   250: aload_0
    //   251: getfield 11	com/taplytics/dn:a	Lcom/taplytics/dg;
    //   254: invokestatic 36	com/taplytics/dg:d	(Lcom/taplytics/dg;)Ljava/lang/Class;
    //   257: if_acmpne +446 -> 703
    //   260: invokestatic 100	com/taplytics/ck:c	()Z
    //   263: ifeq +29 -> 292
    //   266: new 102	java/lang/StringBuilder
    //   269: dup
    //   270: invokespecial 103	java/lang/StringBuilder:<init>	()V
    //   273: ldc -127
    //   275: invokevirtual 109	java/lang/StringBuilder:append	(Ljava/lang/String;)Ljava/lang/StringBuilder;
    //   278: aload 7
    //   280: invokevirtual 90	java/lang/Class:getCanonicalName	()Ljava/lang/String;
    //   283: invokevirtual 109	java/lang/StringBuilder:append	(Ljava/lang/String;)Ljava/lang/StringBuilder;
    //   286: invokevirtual 112	java/lang/StringBuilder:toString	()Ljava/lang/String;
    //   289: invokestatic 114	com/taplytics/ck:a	(Ljava/lang/String;)V
    //   292: aload_0
    //   293: getfield 11	com/taplytics/dn:a	Lcom/taplytics/dg;
    //   296: aload 7
    //   298: invokestatic 131	com/taplytics/dg:b	(Lcom/taplytics/dg;Ljava/lang/Class;)Ljava/lang/Class;
    //   301: pop
    //   302: aload_0
    //   303: getfield 11	com/taplytics/dn:a	Lcom/taplytics/dg;
    //   306: invokestatic 33	com/taplytics/dg:c	(Lcom/taplytics/dg;)Ljava/lang/Class;
    //   309: astore_1
    //   310: aload_1
    //   311: ifnull -118 -> 193
    //   314: aload_0
    //   315: getfield 11	com/taplytics/dn:a	Lcom/taplytics/dg;
    //   318: invokestatic 33	com/taplytics/dg:c	(Lcom/taplytics/dg;)Ljava/lang/Class;
    //   321: ifnull +76 -> 397
    //   324: aload_0
    //   325: getfield 11	com/taplytics/dn:a	Lcom/taplytics/dg;
    //   328: invokestatic 33	com/taplytics/dg:c	(Lcom/taplytics/dg;)Ljava/lang/Class;
    //   331: invokevirtual 121	java/lang/Class:getDeclaredMethods	()[Ljava/lang/reflect/Method;
    //   334: astore_1
    //   335: aload_1
    //   336: arraylength
    //   337: istore 4
    //   339: iconst_0
    //   340: istore_2
    //   341: iload_2
    //   342: iload 4
    //   344: if_icmpge +53 -> 397
    //   347: aload_1
    //   348: iload_2
    //   349: aaload
    //   350: astore 6
    //   352: aload 6
    //   354: invokevirtual 127	java/lang/reflect/Method:getReturnType	()Ljava/lang/Class;
    //   357: aload_0
    //   358: getfield 11	com/taplytics/dn:a	Lcom/taplytics/dg;
    //   361: invokestatic 33	com/taplytics/dg:c	(Lcom/taplytics/dg;)Ljava/lang/Class;
    //   364: if_acmpne +242 -> 606
    //   367: aload_0
    //   368: getfield 11	com/taplytics/dn:a	Lcom/taplytics/dg;
    //   371: aload 6
    //   373: invokestatic 134	com/taplytics/dg:a	(Lcom/taplytics/dg;Ljava/lang/reflect/Method;)Ljava/lang/reflect/Method;
    //   376: pop
    //   377: aload_0
    //   378: getfield 11	com/taplytics/dn:a	Lcom/taplytics/dg;
    //   381: invokestatic 26	com/taplytics/dg:a	(Lcom/taplytics/dg;)Ljava/lang/reflect/Method;
    //   384: ifnull +280 -> 664
    //   387: aload_0
    //   388: getfield 11	com/taplytics/dn:a	Lcom/taplytics/dg;
    //   391: invokestatic 29	com/taplytics/dg:b	(Lcom/taplytics/dg;)Ljava/lang/reflect/Method;
    //   394: ifnull +270 -> 664
    //   397: aload_0
    //   398: getfield 11	com/taplytics/dn:a	Lcom/taplytics/dg;
    //   401: invokestatic 29	com/taplytics/dg:b	(Lcom/taplytics/dg;)Ljava/lang/reflect/Method;
    //   404: ifnull +258 -> 662
    //   407: aload_0
    //   408: getfield 11	com/taplytics/dn:a	Lcom/taplytics/dg;
    //   411: invokestatic 26	com/taplytics/dg:a	(Lcom/taplytics/dg;)Ljava/lang/reflect/Method;
    //   414: ifnull +248 -> 662
    //   417: aload_0
    //   418: getfield 11	com/taplytics/dn:a	Lcom/taplytics/dg;
    //   421: getfield 40	com/taplytics/dg:g	[Ljava/lang/reflect/Field;
    //   424: ifnull +238 -> 662
    //   427: aload_0
    //   428: getfield 11	com/taplytics/dn:a	Lcom/taplytics/dg;
    //   431: invokestatic 33	com/taplytics/dg:c	(Lcom/taplytics/dg;)Ljava/lang/Class;
    //   434: ifnull +228 -> 662
    //   437: aload_0
    //   438: getfield 11	com/taplytics/dn:a	Lcom/taplytics/dg;
    //   441: invokestatic 36	com/taplytics/dg:d	(Lcom/taplytics/dg;)Ljava/lang/Class;
    //   444: ifnull +218 -> 662
    //   447: aload_0
    //   448: getfield 11	com/taplytics/dn:a	Lcom/taplytics/dg;
    //   451: invokestatic 29	com/taplytics/dg:b	(Lcom/taplytics/dg;)Ljava/lang/reflect/Method;
    //   454: iconst_1
    //   455: invokevirtual 138	java/lang/reflect/Method:setAccessible	(Z)V
    //   458: aload_0
    //   459: getfield 11	com/taplytics/dn:a	Lcom/taplytics/dg;
    //   462: invokestatic 26	com/taplytics/dg:a	(Lcom/taplytics/dg;)Ljava/lang/reflect/Method;
    //   465: iconst_1
    //   466: invokevirtual 138	java/lang/reflect/Method:setAccessible	(Z)V
    //   469: aload_0
    //   470: getfield 11	com/taplytics/dn:a	Lcom/taplytics/dg;
    //   473: invokestatic 26	com/taplytics/dg:a	(Lcom/taplytics/dg;)Ljava/lang/reflect/Method;
    //   476: aload_0
    //   477: getfield 11	com/taplytics/dn:a	Lcom/taplytics/dg;
    //   480: invokestatic 29	com/taplytics/dg:b	(Lcom/taplytics/dg;)Ljava/lang/reflect/Method;
    //   483: aload_0
    //   484: getfield 11	com/taplytics/dn:a	Lcom/taplytics/dg;
    //   487: invokestatic 36	com/taplytics/dg:d	(Lcom/taplytics/dg;)Ljava/lang/Class;
    //   490: iconst_0
    //   491: anewarray 140	java/lang/Object
    //   494: invokevirtual 144	java/lang/reflect/Method:invoke	(Ljava/lang/Object;[Ljava/lang/Object;)Ljava/lang/Object;
    //   497: iconst_0
    //   498: anewarray 140	java/lang/Object
    //   501: invokevirtual 144	java/lang/reflect/Method:invoke	(Ljava/lang/Object;[Ljava/lang/Object;)Ljava/lang/Object;
    //   504: astore_1
    //   505: aload_1
    //   506: ifnull +156 -> 662
    //   509: aload_0
    //   510: getfield 11	com/taplytics/dn:a	Lcom/taplytics/dg;
    //   513: getfield 40	com/taplytics/dg:g	[Ljava/lang/reflect/Field;
    //   516: astore 6
    //   518: aload 6
    //   520: arraylength
    //   521: istore 4
    //   523: iload_3
    //   524: istore_2
    //   525: iload_2
    //   526: iload 4
    //   528: if_icmpge +134 -> 662
    //   531: aload 6
    //   533: iload_2
    //   534: aaload
    //   535: astore 7
    //   537: aload 7
    //   539: invokevirtual 149	java/lang/reflect/Field:getType	()Ljava/lang/Class;
    //   542: ldc -105
    //   544: if_acmpne +140 -> 684
    //   547: aload 7
    //   549: invokevirtual 149	java/lang/reflect/Field:getType	()Ljava/lang/Class;
    //   552: ldc -103
    //   554: if_acmpeq +130 -> 684
    //   557: aload 7
    //   559: iconst_1
    //   560: invokevirtual 154	java/lang/reflect/Field:setAccessible	(Z)V
    //   563: aload 7
    //   565: aload_1
    //   566: invokevirtual 158	java/lang/reflect/Field:get	(Ljava/lang/Object;)Ljava/lang/Object;
    //   569: checkcast 151	java/util/Map
    //   572: astore 8
    //   574: new 153	com/taplytics/dp
    //   577: dup
    //   578: invokespecial 159	com/taplytics/dp:<init>	()V
    //   581: astore 9
    //   583: aload 8
    //   585: ifnull +10 -> 595
    //   588: aload 9
    //   590: aload 8
    //   592: invokevirtual 163	com/taplytics/dp:putAll	(Ljava/util/Map;)V
    //   595: aload 7
    //   597: aload_1
    //   598: aload 9
    //   600: invokevirtual 167	java/lang/reflect/Field:set	(Ljava/lang/Object;Ljava/lang/Object;)V
    //   603: goto +81 -> 684
    //   606: aload 6
    //   608: invokevirtual 127	java/lang/reflect/Method:getReturnType	()Ljava/lang/Class;
    //   611: aload_0
    //   612: getfield 11	com/taplytics/dn:a	Lcom/taplytics/dg;
    //   615: invokestatic 36	com/taplytics/dg:d	(Lcom/taplytics/dg;)Ljava/lang/Class;
    //   618: if_acmpne -241 -> 377
    //   621: aload 6
    //   623: invokevirtual 171	java/lang/reflect/Method:getParameterTypes	()[Ljava/lang/Class;
    //   626: arraylength
    //   627: ifne -250 -> 377
    //   630: aload_0
    //   631: getfield 11	com/taplytics/dn:a	Lcom/taplytics/dg;
    //   634: aload 6
    //   636: invokestatic 173	com/taplytics/dg:b	(Lcom/taplytics/dg;Ljava/lang/reflect/Method;)Ljava/lang/reflect/Method;
    //   639: pop
    //   640: goto -263 -> 377
    //   643: astore_1
    //   644: aload_1
    //   645: instanceof 175
    //   648: ifeq +23 -> 671
    //   651: aload_1
    //   652: checkcast 175	java/lang/Exception
    //   655: astore_1
    //   656: ldc -79
    //   658: aload_1
    //   659: invokestatic 180	com/taplytics/ck:b	(Ljava/lang/String;Ljava/lang/Exception;)V
    //   662: aconst_null
    //   663: areturn
    //   664: iload_2
    //   665: iconst_1
    //   666: iadd
    //   667: istore_2
    //   668: goto -327 -> 341
    //   671: aconst_null
    //   672: astore_1
    //   673: goto -17 -> 656
    //   676: astore_1
    //   677: goto -484 -> 193
    //   680: astore_1
    //   681: goto -604 -> 77
    //   684: iload_2
    //   685: iconst_1
    //   686: iadd
    //   687: istore_2
    //   688: goto -163 -> 525
    //   691: astore_1
    //   692: aconst_null
    //   693: astore_1
    //   694: goto -582 -> 112
    //   697: astore_1
    //   698: aconst_null
    //   699: astore_1
    //   700: goto -472 -> 228
    //   703: iload_2
    //   704: iconst_1
    //   705: iadd
    //   706: istore_2
    //   707: goto -469 -> 238
    // Local variable table:
    //   start	length	slot	name	signature
    //   0	710	0	this	dn
    //   0	710	1	paramVarArgs	Void[]
    //   237	470	2	i	int
    //   1	523	3	j	int
    //   234	295	4	k	int
    //   84	119	5	bool	boolean
    //   68	567	6	localObject1	Object
    //   75	521	7	localObject2	Object
    //   104	487	8	localObject3	Object
    //   581	18	9	localdp	dp
    // Exception table:
    //   from	to	target	type
    //   2	52	643	java/lang/Throwable
    //   52	77	643	java/lang/Throwable
    //   77	86	643	java/lang/Throwable
    //   186	193	643	java/lang/Throwable
    //   193	202	643	java/lang/Throwable
    //   314	339	643	java/lang/Throwable
    //   352	377	643	java/lang/Throwable
    //   377	397	643	java/lang/Throwable
    //   397	505	643	java/lang/Throwable
    //   509	523	643	java/lang/Throwable
    //   537	583	643	java/lang/Throwable
    //   588	595	643	java/lang/Throwable
    //   595	603	643	java/lang/Throwable
    //   606	640	643	java/lang/Throwable
    //   207	222	676	java/lang/Throwable
    //   232	236	676	java/lang/Throwable
    //   244	292	676	java/lang/Throwable
    //   292	302	676	java/lang/Throwable
    //   302	310	676	java/lang/Throwable
    //   91	106	680	java/lang/Throwable
    //   116	168	680	java/lang/Throwable
    //   168	186	680	java/lang/Throwable
    //   106	112	691	java/lang/Throwable
    //   222	228	697	java/lang/Throwable
  }
}

/* Location:
 * Qualified Name:     com.taplytics.dn
 * Java Class Version: 6 (50.0)
 * JD-Core Version:    0.7.1
 */