package com.taplytics;

import android.content.Context;
import java.lang.reflect.InvocationHandler;

class fv
  implements InvocationHandler
{
  fv(ft paramft, Context paramContext) {}
  
  /* Error */
  public Object invoke(Object paramObject, java.lang.reflect.Method paramMethod, Object[] paramArrayOfObject)
    throws java.lang.Throwable
  {
    // Byte code:
    //   0: aload_2
    //   1: invokevirtual 32	java/lang/reflect/Method:getName	()Ljava/lang/String;
    //   4: astore_1
    //   5: iconst_m1
    //   6: istore 4
    //   8: aload_1
    //   9: invokevirtual 38	java/lang/String:hashCode	()I
    //   12: lookupswitch	default:+36->48, -609996822:+66->78, 147696667:+96->108, 1158766654:+81->93
    //   48: iload 4
    //   50: tableswitch	default:+26->76, 0:+73->123, 1:+337->387, 2:+395->445
    //   76: aconst_null
    //   77: areturn
    //   78: aload_1
    //   79: ldc 40
    //   81: invokevirtual 44	java/lang/String:equals	(Ljava/lang/Object;)Z
    //   84: ifeq -36 -> 48
    //   87: iconst_0
    //   88: istore 4
    //   90: goto -42 -> 48
    //   93: aload_1
    //   94: ldc 46
    //   96: invokevirtual 44	java/lang/String:equals	(Ljava/lang/Object;)Z
    //   99: ifeq -51 -> 48
    //   102: iconst_1
    //   103: istore 4
    //   105: goto -57 -> 48
    //   108: aload_1
    //   109: ldc 47
    //   111: invokevirtual 44	java/lang/String:equals	(Ljava/lang/Object;)Z
    //   114: ifeq -66 -> 48
    //   117: iconst_2
    //   118: istore 4
    //   120: goto -72 -> 48
    //   123: invokestatic 53	com/taplytics/ck:c	()Z
    //   126: ifeq +8 -> 134
    //   129: ldc 55
    //   131: invokestatic 58	com/taplytics/ck:a	(Ljava/lang/String;)V
    //   134: aload_0
    //   135: getfield 14	com/taplytics/fv:b	Lcom/taplytics/ft;
    //   138: invokestatic 63	com/taplytics/ft:b	(Lcom/taplytics/ft;)Ljava/util/List;
    //   141: ifnull +94 -> 235
    //   144: aload_0
    //   145: getfield 14	com/taplytics/fv:b	Lcom/taplytics/ft;
    //   148: invokestatic 63	com/taplytics/ft:b	(Lcom/taplytics/ft;)Ljava/util/List;
    //   151: invokeinterface 68 1 0
    //   156: istore 5
    //   158: iload 5
    //   160: ifne +75 -> 235
    //   163: aload_0
    //   164: getfield 14	com/taplytics/fv:b	Lcom/taplytics/ft;
    //   167: aload_0
    //   168: getfield 14	com/taplytics/fv:b	Lcom/taplytics/ft;
    //   171: invokestatic 71	com/taplytics/ft:c	(Lcom/taplytics/ft;)Lcom/taplytics/m;
    //   174: invokevirtual 76	com/taplytics/m:a	()Ljava/lang/Object;
    //   177: aload_0
    //   178: getfield 14	com/taplytics/fv:b	Lcom/taplytics/ft;
    //   181: invokestatic 63	com/taplytics/ft:b	(Lcom/taplytics/ft;)Ljava/util/List;
    //   184: invokestatic 79	com/taplytics/ft:a	(Lcom/taplytics/ft;Ljava/lang/Object;Ljava/util/List;)V
    //   187: invokestatic 53	com/taplytics/ck:c	()Z
    //   190: ifeq +36 -> 226
    //   193: new 81	java/lang/StringBuilder
    //   196: dup
    //   197: invokespecial 82	java/lang/StringBuilder:<init>	()V
    //   200: aload_0
    //   201: getfield 14	com/taplytics/fv:b	Lcom/taplytics/ft;
    //   204: invokestatic 63	com/taplytics/ft:b	(Lcom/taplytics/ft;)Ljava/util/List;
    //   207: invokeinterface 85 1 0
    //   212: invokevirtual 89	java/lang/StringBuilder:append	(I)Ljava/lang/StringBuilder;
    //   215: ldc 91
    //   217: invokevirtual 94	java/lang/StringBuilder:append	(Ljava/lang/String;)Ljava/lang/StringBuilder;
    //   220: invokevirtual 97	java/lang/StringBuilder:toString	()Ljava/lang/String;
    //   223: invokestatic 58	com/taplytics/ck:a	(Ljava/lang/String;)V
    //   226: aload_0
    //   227: getfield 14	com/taplytics/fv:b	Lcom/taplytics/ft;
    //   230: aconst_null
    //   231: invokestatic 100	com/taplytics/ft:a	(Lcom/taplytics/ft;Ljava/util/List;)Ljava/util/List;
    //   234: pop
    //   235: aload_0
    //   236: getfield 14	com/taplytics/fv:b	Lcom/taplytics/ft;
    //   239: invokestatic 104	com/taplytics/ft:d	(Lcom/taplytics/ft;)Ljava/lang/Object;
    //   242: astore_1
    //   243: aload_1
    //   244: ifnull +70 -> 314
    //   247: aload_0
    //   248: getfield 14	com/taplytics/fv:b	Lcom/taplytics/ft;
    //   251: aload_0
    //   252: getfield 14	com/taplytics/fv:b	Lcom/taplytics/ft;
    //   255: invokestatic 71	com/taplytics/ft:c	(Lcom/taplytics/ft;)Lcom/taplytics/m;
    //   258: invokevirtual 76	com/taplytics/m:a	()Ljava/lang/Object;
    //   261: aload_0
    //   262: getfield 14	com/taplytics/fv:b	Lcom/taplytics/ft;
    //   265: invokestatic 104	com/taplytics/ft:d	(Lcom/taplytics/ft;)Ljava/lang/Object;
    //   268: aload_0
    //   269: getfield 16	com/taplytics/fv:a	Landroid/content/Context;
    //   272: iconst_0
    //   273: new 106	android/content/Intent
    //   276: dup
    //   277: aload_0
    //   278: getfield 16	com/taplytics/fv:a	Landroid/content/Context;
    //   281: ldc 108
    //   283: invokespecial 111	android/content/Intent:<init>	(Landroid/content/Context;Ljava/lang/Class;)V
    //   286: ldc 112
    //   288: invokestatic 118	android/app/PendingIntent:getService	(Landroid/content/Context;ILandroid/content/Intent;I)Landroid/app/PendingIntent;
    //   291: invokestatic 121	com/taplytics/ft:a	(Lcom/taplytics/ft;Ljava/lang/Object;Ljava/lang/Object;Landroid/app/PendingIntent;)V
    //   294: invokestatic 53	com/taplytics/ck:c	()Z
    //   297: ifeq +8 -> 305
    //   300: ldc 123
    //   302: invokestatic 58	com/taplytics/ck:a	(Ljava/lang/String;)V
    //   305: aload_0
    //   306: getfield 14	com/taplytics/fv:b	Lcom/taplytics/ft;
    //   309: aconst_null
    //   310: invokestatic 126	com/taplytics/ft:a	(Lcom/taplytics/ft;Ljava/lang/Object;)Ljava/lang/Object;
    //   313: pop
    //   314: aload_0
    //   315: getfield 14	com/taplytics/fv:b	Lcom/taplytics/ft;
    //   318: invokestatic 71	com/taplytics/ft:c	(Lcom/taplytics/ft;)Lcom/taplytics/m;
    //   321: ldc -128
    //   323: invokevirtual 131	com/taplytics/m:a	(Ljava/lang/String;)Ljava/lang/Object;
    //   326: pop
    //   327: aload_0
    //   328: getfield 14	com/taplytics/fv:b	Lcom/taplytics/ft;
    //   331: invokestatic 134	com/taplytics/ft:a	(Lcom/taplytics/ft;)Lcom/taplytics/es;
    //   334: ifnull -258 -> 76
    //   337: aload_0
    //   338: getfield 14	com/taplytics/fv:b	Lcom/taplytics/ft;
    //   341: invokestatic 134	com/taplytics/ft:a	(Lcom/taplytics/ft;)Lcom/taplytics/es;
    //   344: invokeinterface 138 1 0
    //   349: aconst_null
    //   350: areturn
    //   351: astore_1
    //   352: new 81	java/lang/StringBuilder
    //   355: dup
    //   356: invokespecial 82	java/lang/StringBuilder:<init>	()V
    //   359: ldc -116
    //   361: invokevirtual 94	java/lang/StringBuilder:append	(Ljava/lang/String;)Ljava/lang/StringBuilder;
    //   364: aload_1
    //   365: invokevirtual 143	java/lang/Exception:getMessage	()Ljava/lang/String;
    //   368: invokevirtual 94	java/lang/StringBuilder:append	(Ljava/lang/String;)Ljava/lang/StringBuilder;
    //   371: invokevirtual 97	java/lang/StringBuilder:toString	()Ljava/lang/String;
    //   374: invokestatic 145	com/taplytics/ck:c	(Ljava/lang/String;)V
    //   377: aconst_null
    //   378: areturn
    //   379: astore_1
    //   380: aload_1
    //   381: invokevirtual 148	java/lang/Exception:printStackTrace	()V
    //   384: goto -197 -> 187
    //   387: invokestatic 53	com/taplytics/ck:c	()Z
    //   390: ifeq +33 -> 423
    //   393: new 81	java/lang/StringBuilder
    //   396: dup
    //   397: invokespecial 82	java/lang/StringBuilder:<init>	()V
    //   400: ldc -106
    //   402: invokevirtual 94	java/lang/StringBuilder:append	(Ljava/lang/String;)Ljava/lang/StringBuilder;
    //   405: aload_3
    //   406: iconst_0
    //   407: aaload
    //   408: checkcast 152	java/lang/Integer
    //   411: invokevirtual 155	java/lang/Integer:intValue	()I
    //   414: invokevirtual 89	java/lang/StringBuilder:append	(I)Ljava/lang/StringBuilder;
    //   417: invokevirtual 97	java/lang/StringBuilder:toString	()Ljava/lang/String;
    //   420: invokestatic 58	com/taplytics/ck:a	(Ljava/lang/String;)V
    //   423: aload_0
    //   424: getfield 14	com/taplytics/fv:b	Lcom/taplytics/ft;
    //   427: invokestatic 134	com/taplytics/ft:a	(Lcom/taplytics/ft;)Lcom/taplytics/es;
    //   430: ifnull +15 -> 445
    //   433: aload_0
    //   434: getfield 14	com/taplytics/fv:b	Lcom/taplytics/ft;
    //   437: invokestatic 134	com/taplytics/ft:a	(Lcom/taplytics/ft;)Lcom/taplytics/es;
    //   440: invokeinterface 138 1 0
    //   445: aload_0
    //   446: invokevirtual 156	java/lang/Object:hashCode	()I
    //   449: invokestatic 160	java/lang/Integer:valueOf	(I)Ljava/lang/Integer;
    //   452: areturn
    //   453: astore_1
    //   454: goto -160 -> 294
    // Local variable table:
    //   start	length	slot	name	signature
    //   0	457	0	this	fv
    //   0	457	1	paramObject	Object
    //   0	457	2	paramMethod	java.lang.reflect.Method
    //   0	457	3	paramArrayOfObject	Object[]
    //   6	113	4	i	int
    //   156	3	5	bool	boolean
    // Exception table:
    //   from	to	target	type
    //   123	134	351	java/lang/Exception
    //   134	158	351	java/lang/Exception
    //   187	226	351	java/lang/Exception
    //   226	235	351	java/lang/Exception
    //   235	243	351	java/lang/Exception
    //   294	305	351	java/lang/Exception
    //   305	314	351	java/lang/Exception
    //   314	349	351	java/lang/Exception
    //   380	384	351	java/lang/Exception
    //   163	187	379	java/lang/Exception
    //   247	294	453	java/lang/Exception
  }
}

/* Location:
 * Qualified Name:     com.taplytics.fv
 * Java Class Version: 6 (50.0)
 * JD-Core Version:    0.7.1
 */