package com.paypal.android.sdk;

import android.os.Handler;

public class bo
  extends bu
{
  private static final String a = bo.class.getSimpleName();
  private Handler b;
  private String c;
  private String d;
  private String e;
  private y f;
  
  public bo(String paramString1, String paramString2, String paramString3, y paramy, Handler paramHandler)
  {
    b = paramHandler;
    c = paramString1;
    d = paramString2;
    e = paramString3;
    f = paramy;
  }
  
  /* Error */
  public void run()
  {
    // Byte code:
    //   0: aload_0
    //   1: getfield 30	com/paypal/android/sdk/bo:b	Landroid/os/Handler;
    //   4: ifnonnull +4 -> 8
    //   7: return
    //   8: aconst_null
    //   9: astore_3
    //   10: aload_0
    //   11: getfield 30	com/paypal/android/sdk/bo:b	Landroid/os/Handler;
    //   14: aload_0
    //   15: getfield 30	com/paypal/android/sdk/bo:b	Landroid/os/Handler;
    //   18: bipush 20
    //   20: aload_0
    //   21: getfield 32	com/paypal/android/sdk/bo:c	Ljava/lang/String;
    //   24: invokestatic 47	android/os/Message:obtain	(Landroid/os/Handler;ILjava/lang/Object;)Landroid/os/Message;
    //   27: invokevirtual 53	android/os/Handler:sendMessage	(Landroid/os/Message;)Z
    //   30: pop
    //   31: new 55	org/apache/http/impl/client/DefaultHttpClient
    //   34: dup
    //   35: invokespecial 56	org/apache/http/impl/client/DefaultHttpClient:<init>	()V
    //   38: astore_2
    //   39: aload_2
    //   40: invokeinterface 62 1 0
    //   45: sipush 10000
    //   48: invokestatic 68	org/apache/http/params/HttpConnectionParams:setSoTimeout	(Lorg/apache/http/params/HttpParams;I)V
    //   51: aload_2
    //   52: invokeinterface 62 1 0
    //   57: sipush 10000
    //   60: invokestatic 71	org/apache/http/params/HttpConnectionParams:setConnectionTimeout	(Lorg/apache/http/params/HttpParams;I)V
    //   63: new 73	org/apache/http/client/methods/HttpGet
    //   66: dup
    //   67: aload_0
    //   68: getfield 32	com/paypal/android/sdk/bo:c	Ljava/lang/String;
    //   71: invokespecial 76	org/apache/http/client/methods/HttpGet:<init>	(Ljava/lang/String;)V
    //   74: astore_1
    //   75: aload_1
    //   76: ldc 78
    //   78: ldc 80
    //   80: iconst_4
    //   81: anewarray 82	java/lang/Object
    //   84: dup
    //   85: iconst_0
    //   86: aload_0
    //   87: getfield 38	com/paypal/android/sdk/bo:f	Lcom/paypal/android/sdk/y;
    //   90: invokevirtual 86	com/paypal/android/sdk/y:a	()Ljava/lang/String;
    //   93: aastore
    //   94: dup
    //   95: iconst_1
    //   96: aload_0
    //   97: getfield 38	com/paypal/android/sdk/bo:f	Lcom/paypal/android/sdk/y;
    //   100: invokevirtual 88	com/paypal/android/sdk/y:b	()Ljava/lang/String;
    //   103: aastore
    //   104: dup
    //   105: iconst_2
    //   106: aload_0
    //   107: getfield 36	com/paypal/android/sdk/bo:e	Ljava/lang/String;
    //   110: aastore
    //   111: dup
    //   112: iconst_3
    //   113: aload_0
    //   114: getfield 34	com/paypal/android/sdk/bo:d	Ljava/lang/String;
    //   117: aastore
    //   118: invokestatic 94	java/lang/String:format	(Ljava/lang/String;[Ljava/lang/Object;)Ljava/lang/String;
    //   121: invokevirtual 98	org/apache/http/client/methods/HttpGet:setHeader	(Ljava/lang/String;Ljava/lang/String;)V
    //   124: aload_1
    //   125: ldc 100
    //   127: ldc 102
    //   129: invokevirtual 98	org/apache/http/client/methods/HttpGet:setHeader	(Ljava/lang/String;Ljava/lang/String;)V
    //   132: getstatic 23	com/paypal/android/sdk/bo:a	Ljava/lang/String;
    //   135: ldc 80
    //   137: iconst_4
    //   138: anewarray 82	java/lang/Object
    //   141: dup
    //   142: iconst_0
    //   143: aload_0
    //   144: getfield 38	com/paypal/android/sdk/bo:f	Lcom/paypal/android/sdk/y;
    //   147: invokevirtual 86	com/paypal/android/sdk/y:a	()Ljava/lang/String;
    //   150: aastore
    //   151: dup
    //   152: iconst_1
    //   153: aload_0
    //   154: getfield 38	com/paypal/android/sdk/bo:f	Lcom/paypal/android/sdk/y;
    //   157: invokevirtual 88	com/paypal/android/sdk/y:b	()Ljava/lang/String;
    //   160: aastore
    //   161: dup
    //   162: iconst_2
    //   163: aload_0
    //   164: getfield 36	com/paypal/android/sdk/bo:e	Ljava/lang/String;
    //   167: aastore
    //   168: dup
    //   169: iconst_3
    //   170: aload_0
    //   171: getfield 34	com/paypal/android/sdk/bo:d	Ljava/lang/String;
    //   174: aastore
    //   175: invokestatic 94	java/lang/String:format	(Ljava/lang/String;[Ljava/lang/Object;)Ljava/lang/String;
    //   178: invokestatic 106	com/paypal/android/sdk/ch:a	(Ljava/lang/String;Ljava/lang/String;)V
    //   181: new 108	java/io/BufferedReader
    //   184: dup
    //   185: new 110	java/io/InputStreamReader
    //   188: dup
    //   189: aload_2
    //   190: aload_1
    //   191: invokeinterface 114 2 0
    //   196: invokeinterface 120 1 0
    //   201: invokeinterface 126 1 0
    //   206: ldc -128
    //   208: invokespecial 131	java/io/InputStreamReader:<init>	(Ljava/io/InputStream;Ljava/lang/String;)V
    //   211: invokespecial 134	java/io/BufferedReader:<init>	(Ljava/io/Reader;)V
    //   214: astore_1
    //   215: new 136	java/lang/StringBuilder
    //   218: dup
    //   219: invokespecial 137	java/lang/StringBuilder:<init>	()V
    //   222: astore_3
    //   223: aload_1
    //   224: invokevirtual 140	java/io/BufferedReader:readLine	()Ljava/lang/String;
    //   227: astore 4
    //   229: aload 4
    //   231: ifnull +59 -> 290
    //   234: aload_3
    //   235: aload 4
    //   237: invokevirtual 144	java/lang/StringBuilder:append	(Ljava/lang/String;)Ljava/lang/StringBuilder;
    //   240: pop
    //   241: goto -18 -> 223
    //   244: astore_3
    //   245: aload_0
    //   246: getfield 30	com/paypal/android/sdk/bo:b	Landroid/os/Handler;
    //   249: aload_0
    //   250: getfield 30	com/paypal/android/sdk/bo:b	Landroid/os/Handler;
    //   253: bipush 21
    //   255: aload_3
    //   256: invokestatic 47	android/os/Message:obtain	(Landroid/os/Handler;ILjava/lang/Object;)Landroid/os/Message;
    //   259: invokevirtual 53	android/os/Handler:sendMessage	(Landroid/os/Message;)Z
    //   262: pop
    //   263: aload_1
    //   264: invokestatic 149	com/paypal/android/sdk/ft:a	(Ljava/io/Closeable;)V
    //   267: aload_2
    //   268: ifnull +14 -> 282
    //   271: aload_2
    //   272: invokeinterface 153 1 0
    //   277: invokeinterface 158 1 0
    //   282: invokestatic 163	com/paypal/android/sdk/bv:a	()Lcom/paypal/android/sdk/bv;
    //   285: aload_0
    //   286: invokevirtual 166	com/paypal/android/sdk/bv:b	(Lcom/paypal/android/sdk/bu;)V
    //   289: return
    //   290: aload_0
    //   291: getfield 30	com/paypal/android/sdk/bo:b	Landroid/os/Handler;
    //   294: aload_0
    //   295: getfield 30	com/paypal/android/sdk/bo:b	Landroid/os/Handler;
    //   298: bipush 22
    //   300: aload_3
    //   301: invokevirtual 169	java/lang/StringBuilder:toString	()Ljava/lang/String;
    //   304: invokestatic 47	android/os/Message:obtain	(Landroid/os/Handler;ILjava/lang/Object;)Landroid/os/Message;
    //   307: invokevirtual 53	android/os/Handler:sendMessage	(Landroid/os/Message;)Z
    //   310: pop
    //   311: aload_1
    //   312: invokestatic 149	com/paypal/android/sdk/ft:a	(Ljava/io/Closeable;)V
    //   315: aload_2
    //   316: invokeinterface 153 1 0
    //   321: invokeinterface 158 1 0
    //   326: invokestatic 163	com/paypal/android/sdk/bv:a	()Lcom/paypal/android/sdk/bv;
    //   329: aload_0
    //   330: invokevirtual 166	com/paypal/android/sdk/bv:b	(Lcom/paypal/android/sdk/bu;)V
    //   333: return
    //   334: astore_1
    //   335: aconst_null
    //   336: astore_2
    //   337: aload_3
    //   338: invokestatic 149	com/paypal/android/sdk/ft:a	(Ljava/io/Closeable;)V
    //   341: aload_2
    //   342: ifnull +14 -> 356
    //   345: aload_2
    //   346: invokeinterface 153 1 0
    //   351: invokeinterface 158 1 0
    //   356: invokestatic 163	com/paypal/android/sdk/bv:a	()Lcom/paypal/android/sdk/bv;
    //   359: aload_0
    //   360: invokevirtual 166	com/paypal/android/sdk/bv:b	(Lcom/paypal/android/sdk/bu;)V
    //   363: aload_1
    //   364: athrow
    //   365: astore_1
    //   366: goto -29 -> 337
    //   369: astore 4
    //   371: aload_1
    //   372: astore_3
    //   373: aload 4
    //   375: astore_1
    //   376: goto -39 -> 337
    //   379: astore 4
    //   381: aload_1
    //   382: astore_3
    //   383: aload 4
    //   385: astore_1
    //   386: goto -49 -> 337
    //   389: astore_3
    //   390: aconst_null
    //   391: astore_2
    //   392: aconst_null
    //   393: astore_1
    //   394: goto -149 -> 245
    //   397: astore_3
    //   398: aconst_null
    //   399: astore_1
    //   400: goto -155 -> 245
    // Local variable table:
    //   start	length	slot	name	signature
    //   0	403	0	this	bo
    //   74	238	1	localObject1	Object
    //   334	30	1	localObject2	Object
    //   365	7	1	localObject3	Object
    //   375	25	1	localObject4	Object
    //   38	354	2	localDefaultHttpClient	org.apache.http.impl.client.DefaultHttpClient
    //   9	226	3	localStringBuilder	StringBuilder
    //   244	94	3	localException1	Exception
    //   372	11	3	localObject5	Object
    //   389	1	3	localException2	Exception
    //   397	1	3	localException3	Exception
    //   227	9	4	str	String
    //   369	5	4	localObject6	Object
    //   379	5	4	localObject7	Object
    // Exception table:
    //   from	to	target	type
    //   215	223	244	java/lang/Exception
    //   223	229	244	java/lang/Exception
    //   234	241	244	java/lang/Exception
    //   290	311	244	java/lang/Exception
    //   10	39	334	finally
    //   39	215	365	finally
    //   215	223	369	finally
    //   223	229	369	finally
    //   234	241	369	finally
    //   290	311	369	finally
    //   245	263	379	finally
    //   10	39	389	java/lang/Exception
    //   39	215	397	java/lang/Exception
  }
}

/* Location:
 * Qualified Name:     com.paypal.android.sdk.bo
 * Java Class Version: 6 (50.0)
 * JD-Core Version:    0.7.1
 */